llm_structured_summary/__init__.py
llm_structured_summary/main.py
llm_structured_summary/prompts.py
llm_structured_summary-2025.12.21124656.dist-info/METADATA
llm_structured_summary-2025.12.21124656.dist-info/WHEEL
llm_structured_summary-2025.12.21124656.dist-info/top_level.txt
llm_structured_summary-2025.12.21124656.dist-info/RECORD
