Metadata-Version: 2.4
Name: llm-structured-summary
Version: 2025.12.21124656
Summary: This package would process text input, such as a research paper title or abstract snippet, and generate a structured summary of the core idea or problem addressed. It uses an LLM to interpret the inpu
Author-email: llm-structured-summary <hi@eugene.plus>
License: MIT
Project-URL: Homepage, https://github.com/chigwell/llm-structured-summary
Requires-Python: >=3.9
Requires-Dist: langchain-llm7>=0.0.0
Requires-Dist: llmatch-messages>=0.0.0
Requires-Dist: langchain-core>=0.3.0
